<?xml version="1.0" encoding="UTF-8"?>
<file name="p.lond.4.1434" TM="19879" HGV="19879" lang="grc" textpart="Fol10b,1">
  <text>
    <sentence id="1">
      <word wordref_id="2101094" id="1" texid="19879" row="271" wordNum="1" hand="m1" regularized="|gap=unknown|" original="|gap=unknown|" completeness="incomplete" tag="" lemma="" lemmaFlag="suspect" perseusTag=""/>
      <word wordref_id="2101095" id="2" texid="19879" row="271" wordNum="2" hand="m1" regularized="á¼…Î¼Î¼Î±Ï„Î±" original="[á¼…]Î¼Î¼Î±(Ï„Î±)" completeness="partly_reconstructed" tag="noun.pl.neut.nom" lemma="á¼…Î¼Î¼Î±" lemmaFlag="ok" perseusTag="n-p---nn-"/>
      <word wordref_id="2101096" id="3" texid="19879" row="271" wordNum="3" hand="m1" regularized="Î¹Î³|digit=13|" original="Î¹Î³|digit=13|" completeness="complete" tag="numeral.none.none.none" lemma="Î¹Î³" lemmaFlag="ok" perseusTag="m--------"/>
      <word wordref_id="2101097" id="4" texid="19879" row="271" wordNum="4" hand="m1" regularized="Î¾Î¿ÎÎ´ÎµÏ‚" original="Î¾Î¿ÎÎ´(ÎµÏ‚)" completeness="complete" tag="noun.pl.fem.nom" lemma="Î¾Î¿Î¯Ï‚" lemmaFlag="suspect" perseusTag="n-p---fn-"/>
      <word wordref_id="2101098" id="5" texid="19879" row="271" wordNum="5" hand="m1" regularized="Î¹Î³|digit=13|" original="Î¹Î³Ì£|digit=13|" completeness="complete" tag="numeral.none.none.none" lemma="Î¹Î³" lemmaFlag="ok" perseusTag="m--------"/>
      <word wordref_id="2101099" id="6" texid="19879" row="272" wordNum="1" hand="m1" regularized="|gap=unknown|" original="|gap=unknown|" completeness="incomplete" tag="" lemma="" lemmaFlag="suspect" perseusTag=""/>
      <word wordref_id="2101100" id="7" texid="19879" row="272" wordNum="2" hand="m1" regularized="á¼€Î³Î³Î±ÏÎµÏ…Ï„Î±á½¶" original="[á¼€Î³]Î³(Î±ÏÎµÏ…Ï„Î±á½¶)" completeness="partly_reconstructed" tag="noun.pl.masc.nom" lemma="á¼€Î³Î³Î±ÏÎµÏ…Ï„Î®Ï‚" lemmaFlag="ok" perseusTag="n-p---mn-"/>
      <word wordref_id="2101101" id="8" texid="19879" row="272" wordNum="3" hand="m1" regularized="Î¹|digit=10|" original="Î¹|digit=10|" completeness="complete" tag="numeral.none.none.none" lemma="Î¹" lemmaFlag="ok" perseusTag="m--------"/>
      <word wordref_id="2101102" id="9" texid="19879" row="272" wordNum="4" hand="m1" regularized="á¼…Î¼Î¼Î±Ï„Î±" original="á¼…Î¼Î¼(Î±Ï„Î±)" completeness="complete" tag="noun.pl.neut.nom" lemma="á¼…Î¼Î¼Î±" lemmaFlag="ok" perseusTag="n-p---nn-"/>
      <word wordref_id="2101103" id="10" texid="19879" row="272" wordNum="5" hand="m1" regularized="Î³|digit=3|" original="Î³|digit=3|" completeness="complete" tag="numeral.none.none.none" lemma="Î³" lemmaFlag="ok" perseusTag="m--------"/>
      <word wordref_id="2101104" id="11" texid="19879" row="272" wordNum="6" hand="m1" regularized="Î¾Î¿ÎÎ´ÎµÏ‚" original="Î¾Î¿[ÎÎ´(ÎµÏ‚)]" completeness="partly_reconstructed" tag="noun.pl.fem.nom" lemma="Î¾Î¿Î¯Ï‚" lemmaFlag="suspect" perseusTag="n-p---fn-"/>
      <word wordref_id="2101105" id="12" texid="19879" row="272" wordNum="7" hand="m1" regularized="|gap=1|" original="|gap=1|" completeness="incomplete" tag="" lemma="" lemmaFlag="suspect" perseusTag=""/>
      <word wordref_id="2101106" id="13" texid="19879" row="273" wordNum="1" hand="m1" regularized="|gap=unknown|" original="|gap=unknown|" completeness="incomplete" tag="" lemma="" lemmaFlag="suspect" perseusTag=""/>
      <word wordref_id="2101107" id="14" texid="19879" row="273" wordNum="2" hand="m1" regularized="Î³|digit=3|" original="Î³|digit=3|" completeness="complete" tag="numeral.none.none.none" lemma="Î³" lemmaFlag="ok" perseusTag="m--------"/>
      <word wordref_id="2101108" id="15" texid="19879" row="273" wordNum="3" hand="m1" regularized="Î²|digit=2|" original="Î²|digit=2|" completeness="complete" tag="numeral.none.none.none" lemma="Î²" lemmaFlag="ok" perseusTag="m--------"/>
      <word wordref_id="2101109" id="16" texid="19879" row="273" wordNum="4" hand="m1" regularized="|gap=1|" original="|gap=1|" completeness="incomplete" tag="" lemma="" lemmaFlag="suspect" perseusTag=""/>
      <word wordref_id="2101110" id="17" texid="19879" row="274" wordNum="1" hand="m1" regularized="|gap=unknown|" original="|gap=unknown|" completeness="incomplete" tag="" lemma="" lemmaFlag="suspect" perseusTag=""/>
      <word wordref_id="2101111" id="18" texid="19879" row="274" wordNum="2" hand="m1" regularized="Î²|digit=2|" original="Î²Ì£|digit=2|" completeness="complete" tag="numeral.none.none.none" lemma="Î²" lemmaFlag="ok" perseusTag="m--------"/>
      <word wordref_id="2101112" id="19" texid="19879" row="274" wordNum="3" hand="m1" regularized="|slanting-stroke|" original="|slanting-stroke|" completeness="complete" tag="" lemma="" lemmaFlag="suspect" perseusTag=""/>
      <word wordref_id="2101113" id="20" texid="19879" row="274" wordNum="4" hand="m1" regularized="|slanting-stroke|" original="|slanting-stroke|" completeness="complete" tag="" lemma="" lemmaFlag="suspect" perseusTag=""/>
      <word wordref_id="2101114" id="21" texid="19879" row="274" wordNum="5" hand="m1" regularized="|gap=1|" original="|gap=1|" completeness="incomplete" tag="" lemma="" lemmaFlag="suspect" perseusTag=""/>
      <word wordref_id="2101115" id="22" texid="19879" row="275" wordNum="1" hand="m1" regularized="|gap=unknown|" original="|gap=unknown|" completeness="incomplete" tag="" lemma="" lemmaFlag="suspect" perseusTag=""/>
      <word wordref_id="2101116" id="23" texid="19879" row="275" wordNum="2" hand="m1" regularized="|slanting-stroke|" original="|slanting-stroke|" completeness="complete" tag="" lemma="" lemmaFlag="suspect" perseusTag=""/>
      <word wordref_id="2101117" id="24" texid="19879" row="275" wordNum="3" hand="m1" regularized="|slanting-stroke|" original="|slanting-stroke|" completeness="complete" tag="" lemma="" lemmaFlag="suspect" perseusTag=""/>
      <word wordref_id="2101118" id="25" texid="19879" row="275" wordNum="4" hand="m1" regularized="|slanting-stroke|" original="|slanting-stroke|" completeness="complete" tag="" lemma="" lemmaFlag="suspect" perseusTag=""/>
      <word wordref_id="2101119" id="26" texid="19879" row="275" wordNum="5" hand="m1" regularized="|slanting-stroke|" original="|slanting-stroke|" completeness="complete" tag="" lemma="" lemmaFlag="suspect" perseusTag=""/>
      <word wordref_id="2101120" id="27" texid="19879" row="275" wordNum="6" hand="m1" regularized="ÏƒÏ€Ï…ÏÎ¯Î´ÎµÏ‚" original="ÏƒÏ€Ï…(ÏÎ¯Î´ÎµÏ‚)" completeness="complete" tag="noun.pl.fem.nom" lemma="ÏƒÏ€Ï…ÏÎ¯Ï‚" lemmaFlag="ok" perseusTag="n-p---fn-"/>
      <word wordref_id="2101121" id="28" texid="19879" row="275" wordNum="7" hand="m1" regularized="Î½|digit=50|" original="Î½|digit=50|" completeness="complete" tag="numeral.none.none.none" lemma="Î½" lemmaFlag="ok" perseusTag="m--------"/>
      <word wordref_id="2101122" id="29" texid="19879" row="276" wordNum="1" hand="m1" regularized="|gap=unknown|" original="|gap=unknown|" completeness="incomplete" tag="" lemma="" lemmaFlag="suspect" perseusTag=""/>
      <word wordref_id="2101123" id="30" texid="19879" row="277" wordNum="1" hand="m1" regularized="|gap=unknown|" original="|gap=unknown|" completeness="incomplete" tag="" lemma="" lemmaFlag="suspect" perseusTag=""/>
      <word wordref_id="2101124" id="31" texid="19879" row="277" wordNum="2" hand="m1" regularized="Îµ|digit=5|" original="Îµ|digit=5|" completeness="complete" tag="numeral.none.none.none" lemma="Îµ" lemmaFlag="ok" perseusTag="m--------"/>
      <word wordref_id="2101125" id="32" texid="19879" row="277" wordNum="3" hand="m1" regularized="Î ÎµÎ´Î¹Î¬Î´Ï‰Î½" original="Î ÎµÎ´Î¹Î¬(Î´Ï‰Î½)" completeness="complete" tag="noun.pl.fem.gen" lemma="Î ÎµÎ´Î¹Î¬Ï‚" lemmaFlag="ok" perseusTag="n-p---fg-"/>
      <word wordref_id="2101126" id="33" texid="19879" row="277" wordNum="4" hand="m1" regularized="|gap=2||gap=4|" original="|gap=2||gap=4|" completeness="incomplete" tag="" lemma="" lemmaFlag="suspect" perseusTag=""/>
      <word wordref_id="2101127" id="34" texid="19879" row="277" wordNum="5" hand="m1" regularized="Ï„Î­ÎºÏ„Ï‰Î½" original="Ï„Î­(ÎºÏ„Ï‰Î½)" completeness="complete" tag="noun.sg.masc.nom" lemma="Ï„Î­ÎºÏ„Ï‰Î½" lemmaFlag="ok" perseusTag="n-s---mn-"/>
      <word wordref_id="2101128" id="35" texid="19879" row="277" wordNum="6" hand="m1" regularized="Î±|digit=1|" original="Î±|digit=1|" completeness="complete" tag="numeral.none.none.none" lemma="Î±" lemmaFlag="ok" perseusTag="m--------"/>
      <word wordref_id="2101129" id="36" texid="19879" row="277" wordNum="7" hand="m1" regularized="Î½Î¿Î¼Î¯ÏƒÎ¼Î±Ï„Î±" original="Î½Î¿(Î¼Î¯ÏƒÎ¼Î±Ï„Î±)" completeness="complete" tag="noun.pl.neut.nom" lemma="Î½ÏŒÎ¼Î¹ÏƒÎ¼Î±" lemmaFlag="ok" perseusTag="n-p---nn-"/>
      <word wordref_id="2101130" id="37" texid="19879" row="277" wordNum="8" hand="m1" regularized="Î²|digit=2|" original="Î²|digit=2|" completeness="complete" tag="numeral.none.none.none" lemma="Î²" lemmaFlag="ok" perseusTag="m--------"/>
      <word wordref_id="2101131" id="38" texid="19879" row="277" wordNum="9" hand="m1" regularized="ð…µ|digit=1/2|" original="ð…µ|digit=1/2|" completeness="complete" tag="numeral.none.none.none" lemma="ð…µ" lemmaFlag="ok" perseusTag="m--------"/>
      <word wordref_id="2101132" id="39" texid="19879" row="278" wordNum="1" hand="m1" regularized="|gap=unknown|" original="|gap=unknown|" completeness="incomplete" tag="" lemma="" lemmaFlag="suspect" perseusTag=""/>
      <word wordref_id="2101133" id="40" texid="19879" row="278" wordNum="2" hand="m1" regularized="ÎºÎ±Î»Î±Ï†Î¬Ï„Î¿Ï…" original="ÎºÎ±Î»Î±(Ï†Î¬Ï„Î¿Ï…)" completeness="complete" tag="noun.sg.masc.gen" lemma="ÎºÎ±Î»Î¬Ï†Î±Ï„Î¿Ï‚" lemmaFlag="suspect" perseusTag="n-s---mg-"/>
      <word wordref_id="2101134" id="41" texid="19879" row="278" wordNum="3" hand="m1" regularized="ð…µ|digit=1/2|" original="ð…µ|digit=1/2|" completeness="complete" tag="numeral.none.none.none" lemma="ð…µ" lemmaFlag="ok" perseusTag="m--------"/>
      <word wordref_id="2101135" id="42" texid="19879" row="278" wordNum="4" hand="m1" regularized="Î½ÏŒÎ¼Î¹ÏƒÎ¼Î±" original="Î½ÏŒ(Î¼Î¹ÏƒÎ¼Î±)" completeness="complete" tag="noun.sg.neut.acc" lemma="Î½ÏŒÎ¼Î¹ÏƒÎ¼Î±" lemmaFlag="ok" perseusTag="n-s---na-"/>
      <word wordref_id="2101136" id="43" texid="19879" row="278" wordNum="5" hand="m1" regularized="Î±|digit=1|" original="Î±|digit=1|" completeness="complete" tag="numeral.none.none.none" lemma="Î±" lemmaFlag="ok" perseusTag="m--------"/>
      <word wordref_id="2101137" id="44" texid="19879" row="278" wordNum="6" hand="m1" regularized="ð…µ|digit=1/2|" original="ð…µ|digit=1/2|" completeness="complete" tag="numeral.none.none.none" lemma="ð…µ" lemmaFlag="ok" perseusTag="m--------"/>
      <word wordref_id="2101138" id="45" texid="19879" row="279" wordNum="1" hand="m1" regularized="|gap=unknown|" original="|gap=unknown|" completeness="incomplete" tag="" lemma="" lemmaFlag="suspect" perseusTag=""/>
      <word wordref_id="2101139" id="46" texid="19879" row="279" wordNum="2" hand="m1" regularized="ð…µ|digit=1/2|" original="ð…µ|digit=1/2|" completeness="complete" tag="numeral.none.none.none" lemma="ð…µ" lemmaFlag="ok" perseusTag="m--------"/>
      <word wordref_id="2101140" id="47" texid="19879" row="279" wordNum="3" hand="m1" regularized="Î½ÏŒÎ¼Î¹ÏƒÎ¼Î±" original="Î½ÏŒ(Î¼Î¹ÏƒÎ¼Î±)" completeness="complete" tag="noun.sg.neut.acc" lemma="Î½ÏŒÎ¼Î¹ÏƒÎ¼Î±" lemmaFlag="ok" perseusTag="n-s---na-"/>
      <word wordref_id="2101141" id="48" texid="19879" row="279" wordNum="4" hand="m1" regularized="Î±|digit=1|" original="Î±|digit=1|" completeness="complete" tag="numeral.none.none.none" lemma="Î±" lemmaFlag="ok" perseusTag="m--------"/>
      <word wordref_id="2101142" id="49" texid="19879" row="279" wordNum="5" hand="m1" regularized="ð…µ|digit=1/2|" original="ð…µ|digit=1/2|" completeness="complete" tag="numeral.none.none.none" lemma="ð…µ" lemmaFlag="ok" perseusTag="m--------"/>
      <word wordref_id="2101143" id="50" texid="19879" row="280" wordNum="1" hand="m1" regularized="|gap=unknown|" original="|gap=unknown|" completeness="incomplete" tag="" lemma="" lemmaFlag="suspect" perseusTag=""/>
      <word wordref_id="2101144" id="51" texid="19879" row="280" wordNum="2" hand="m1" regularized="Î±|digit=1|" original="Î±|digit=1|" completeness="complete" tag="numeral.none.none.none" lemma="Î±" lemmaFlag="ok" perseusTag="m--------"/>
      <word wordref_id="2101145" id="52" texid="19879" row="280" wordNum="3" hand="m1" regularized="Î½Î¿Î¼Î¯ÏƒÎ¼Î±Ï„Î±" original="Î½Î¿(Î¼Î¯ÏƒÎ¼Î±Ï„Î±)" completeness="complete" tag="noun.pl.neut.acc" lemma="Î½ÏŒÎ¼Î¹ÏƒÎ¼Î±" lemmaFlag="ok" perseusTag="n-p---na-"/>
      <word wordref_id="2101146" id="53" texid="19879" row="280" wordNum="4" hand="m1" regularized="Î²|digit=2|" original="Î²|digit=2|" completeness="complete" tag="numeral.none.none.none" lemma="Î²" lemmaFlag="ok" perseusTag="m--------"/>
      <word wordref_id="2101147" id="54" texid="19879" row="280" wordNum="5" hand="m1" regularized="ð…µ|digit=1/2|" original="ð…µ|digit=1/2|" completeness="complete" tag="numeral.none.none.none" lemma="ð…µ" lemmaFlag="ok" perseusTag="m--------"/>
      <word wordref_id="2101148" id="55" texid="19879" row="280" wordNum="6" hand="m1" regularized="Ï€ÏÎ¯ÏƒÏ„Î·Ï‚" original="Ï€ÏÎ¯(Ïƒ)Ï„(Î·Ï‚)" completeness="complete" tag="noun.sg.masc.nom" lemma="Ï€ÏÎ¯ÏƒÏ„Î·Ï‚" lemmaFlag="ok" perseusTag="n-s---mn-"/>
      <word wordref_id="2101149" id="56" texid="19879" row="280" wordNum="7" hand="m1" regularized="Î±|digit=1|" original="Î±|digit=1|" completeness="complete" tag="numeral.none.none.none" lemma="Î±" lemmaFlag="ok" perseusTag="m--------"/>
      <word wordref_id="2101150" id="57" texid="19879" row="280" wordNum="8" hand="m1" regularized="Î½Î¿Î¼Î¯ÏƒÎ¼Î±Ï„Î±" original="Î½Î¿(Î¼Î¯ÏƒÎ¼Î±Ï„Î±)" completeness="complete" tag="noun.pl.neut.acc" lemma="Î½ÏŒÎ¼Î¹ÏƒÎ¼Î±" lemmaFlag="ok" perseusTag="n-p---na-"/>
      <word wordref_id="2101151" id="58" texid="19879" row="280" wordNum="9" hand="m1" regularized="Î²|digit=2|" original="Î²|digit=2|" completeness="complete" tag="numeral.none.none.none" lemma="Î²" lemmaFlag="ok" perseusTag="m--------"/>
      <word wordref_id="2101152" id="59" texid="19879" row="280" wordNum="10" hand="m1" regularized="ð…µ|digit=1/2|" original="ð…µ|digit=1/2|" completeness="complete" tag="numeral.none.none.none" lemma="ð…µ" lemmaFlag="ok" perseusTag="m--------"/>
      <word wordref_id="2101153" id="60" texid="19879" row="281" wordNum="1" hand="m1" regularized="|gap=unknown|" original="|gap=unknown|" completeness="incomplete" tag="" lemma="" lemmaFlag="suspect" perseusTag=""/>
      <word wordref_id="2101154" id="61" texid="19879" row="281" wordNum="2" hand="m1" regularized="á¼Î½" original="[á¼Î½]" completeness="fully_reconstructed" tag="preposition" lemma="á¼Î½" lemmaFlag="ok" perseusTag="r--------"/>
      <word wordref_id="2101155" id="62" texid="19879" row="281" wordNum="3" hand="m1" regularized="Ï„á¿‡" original="[Ï„(á¿‡)]" completeness="fully_reconstructed" tag="article.sg.fem.dat" lemma="á½" lemmaFlag="ok" perseusTag="l-s---fd-"/>
      <word wordref_id="2101156" id="63" texid="19879" row="281" wordNum="4" hand="m1" regularized="Î½Î®Ïƒá¿³" original="[Î½]Î®Ì£Ïƒ\á¿³/" completeness="partly_reconstructed" tag="noun.sg.fem.dat" lemma="Î½á¿†ÏƒÎ¿Ï‚" lemmaFlag="ok" perseusTag="n-s---fd-"/>
      <word wordref_id="2101157" id="64" texid="19879" row="281" wordNum="5" hand="m1" regularized="Î’Î±Î²Ï…Î»á¿¶Î½Î¿Ï‚" original="Î’Î±Î²Ï…(Î»á¿¶Î½Î¿Ï‚)" completeness="complete" tag="noun.sg.fem.gen" lemma="Î’Î±Î²Ï…Î»ÏŽÎ½" lemmaFlag="ok" perseusTag="n-s---fg-"/>
      <word wordref_id="2101158" id="65" texid="19879" row="281" wordNum="6" hand="m1" regularized="Î¼Î·Î½á¿¶Î½" original="Î¼(Î·Î½á¿¶Î½)" completeness="complete" tag="noun.pl.masc.gen" lemma="Î¼Î®Î½" lemmaFlag="ok" perseusTag="n-p---mg-"/>
      <word wordref_id="2101159" id="66" texid="19879" row="281" wordNum="7" hand="m1" regularized="Îµ|digit=5|" original="Îµ|digit=5|" completeness="complete" tag="numeral.none.none.none" lemma="Îµ" lemmaFlag="ok" perseusTag="m--------"/>
      <word wordref_id="2101160" id="67" texid="19879" row="282" wordNum="1" hand="m1" regularized="|gap=unknown|" original="|gap=unknown|" completeness="incomplete" tag="" lemma="" lemmaFlag="suspect" perseusTag=""/>
      <word wordref_id="2101161" id="68" texid="19879" row="282" wordNum="2" hand="m1" regularized="Î³|digit=3|" original="Î³|digit=3|" completeness="complete" tag="numeral.none.none.none" lemma="Î³" lemmaFlag="ok" perseusTag="m--------"/>
      <word wordref_id="2101162" id="69" texid="19879" row="282" wordNum="3" hand="m1" regularized="Î ÎµÎ´Î¹Î¬Î´Ï‰Î½" original="Î ÎµÎ´Î¹(Î¬Î´Ï‰Î½)" completeness="complete" tag="noun.pl.fem.gen" lemma="Î ÎµÎ´Î¹Î¬Ï‚" lemmaFlag="ok" perseusTag="n-p---fg-"/>
      <word wordref_id="2101163" id="70" texid="19879" row="282" wordNum="4" hand="m1" regularized="ÎºÎ±Î»Î±Ï†Î¬Ï„Î·Ï‚" original="ÎºÎ±Î»Î±(Ï†Î¬Ï„Î·Ï‚)" completeness="complete" tag="noun.sg.masc.nom" lemma="ÎºÎ±Î»Î±Ï†Î¬Ï„Î·Ï‚" lemmaFlag="suspect" perseusTag="n-s---mn-"/>
      <word wordref_id="2101164" id="71" texid="19879" row="282" wordNum="5" hand="m1" regularized="Î±|digit=1|" original="Î±|digit=1|" completeness="complete" tag="numeral.none.none.none" lemma="Î±" lemmaFlag="ok" perseusTag="m--------"/>
      <word wordref_id="2101165" id="72" texid="19879" row="282" wordNum="6" hand="m1" regularized="Î½Î¿Î¼Î¯ÏƒÎ¼Î±Ï„Î±" original="Î½Î¿(Î¼Î¯ÏƒÎ¼Î±Ï„Î±)" completeness="complete" tag="noun.pl.neut.acc" lemma="Î½ÏŒÎ¼Î¹ÏƒÎ¼Î±" lemmaFlag="ok" perseusTag="n-p---na-"/>
      <word wordref_id="2101166" id="73" texid="19879" row="282" wordNum="7" hand="m1" regularized="Î¶|digit=7|" original="Î¶|digit=7|" completeness="complete" tag="numeral.none.none.none" lemma="Î¶" lemmaFlag="ok" perseusTag="m--------"/>
      <word wordref_id="2101167" id="74" texid="19879" row="282" wordNum="8" hand="m1" regularized="ð…µ|digit=1/2|" original="ð…µ|digit=1/2|" completeness="complete" tag="numeral.none.none.none" lemma="ð…µ" lemmaFlag="ok" perseusTag="m--------"/>
      <word wordref_id="2101168" id="75" texid="19879" row="282" wordNum="9" hand="m1" regularized="á¼€Î³Î³Î±ÏÎµÏ…Ï„á½´Ï‚" original="á¼€Î³Î³(Î±ÏÎµÏ…Ï„á½´Ï‚)" completeness="complete" tag="noun.sg.masc.nom" lemma="á¼€Î³Î³Î±ÏÎµÏ…Ï„Î®Ï‚" lemmaFlag="ok" perseusTag="n-s---mn-"/>
      <word wordref_id="2101169" id="76" texid="19879" row="282" wordNum="10" hand="m1" regularized="Î¨ÏÏÎ¿Ï…" original="Î¨ÏÏÎ¿\Ï…/" completeness="complete" tag="noun.sg.masc.gen" lemma="Î¨Ï…ÏÎ¿Ï‚" lemmaFlag="ok" perseusTag="n-s---mg-"/>
      <word wordref_id="2101170" id="77" texid="19879" row="282" wordNum="11" hand="m1" regularized="ÎºÎ±Î»Î±Ï†Î¬Ï„Î±Î¹" original="ÎºÎ±Î»(Î±Ï†Î¬Ï„Î±Î¹)" completeness="complete" tag="verb.3.sg.pres.ind.mid" lemma="ÎºÎ±Î»Î±Ï†Î¬Ï„Î±Î¹" lemmaFlag="suspect" perseusTag="v3spie---"/>
      <word wordref_id="2101171" id="78" texid="19879" row="282" wordNum="12" hand="m1" regularized="á¼€Î³Î³Î±ÏÎµÏ…Ï„á½´Ï‚" original="á¼€Î³Î³(Î±ÏÎµÏ…Ï„á½´Ï‚)" completeness="complete" tag="noun.sg.masc.nom" lemma="á¼€Î³Î³Î±ÏÎµÏ…Ï„Î®Ï‚" lemmaFlag="ok" perseusTag="n-s---mn-"/>
      <word wordref_id="2101172" id="79" texid="19879" row="282" wordNum="13" hand="m1" regularized="Î±|digit=1|" original="Î±|digit=1|" completeness="complete" tag="numeral.none.none.none" lemma="Î±" lemmaFlag="ok" perseusTag="m--------"/>
      <word wordref_id="2101173" id="80" texid="19879" row="282" wordNum="14" hand="m1" regularized="Î½Î¿Î¼Î¯ÏƒÎ¼Î±Ï„Î±" original="Î½Î¿(Î¼Î¯ÏƒÎ¼Î±Ï„Î±)" completeness="complete" tag="noun.pl.neut.acc" lemma="Î½ÏŒÎ¼Î¹ÏƒÎ¼Î±" lemmaFlag="ok" perseusTag="n-p---na-"/>
      <word wordref_id="2101174" id="81" texid="19879" row="282" wordNum="15" hand="m1" regularized="Î³|digit=3|" original="Î³|digit=3|" completeness="complete" tag="numeral.none.none.none" lemma="Î³" lemmaFlag="ok" perseusTag="m--------"/>
      <word wordref_id="2101175" id="82" texid="19879" row="282" wordNum="16" hand="m1" regularized="ð…µ|digit=1/2|" original="ð…µ|digit=1/2|" completeness="complete" tag="numeral.none.none.none" lemma="ð…µ" lemmaFlag="ok" perseusTag="m--------"/>
      <word wordref_id="2101176" id="83" texid="19879" row="282" wordNum="17" hand="m1" regularized="Î´Â´|digit=1/4|" original="Î´Â´|digit=1/4|" completeness="complete" tag="numeral.none.none.none" lemma="Î´Â´" lemmaFlag="ok" perseusTag="m--------"/>
      <word wordref_id="2101177" id="84" texid="19879" row="283" wordNum="1" hand="m1" regularized="|gap=unknown|" original="|gap=unknown|" completeness="incomplete" tag="" lemma="" lemmaFlag="suspect" perseusTag=""/>
      <word wordref_id="2101178" id="85" texid="19879" row="283" wordNum="2" hand="m1" regularized="ÎºÎ±Î»Î±Ï†Î¬Ï„Î·Ï‚" original="[ÎºÎ±Î»Î±(Ï†Î¬Ï„Î·Ï‚)]" completeness="fully_reconstructed" tag="noun.sg.fem.gen" lemma="ÎºÎ±Î»Î±Ï†Î¬Ï„Î·" lemmaFlag="suspect" perseusTag="n-s---fg-"/>
      <word wordref_id="2101179" id="86" texid="19879" row="283" wordNum="3" hand="m1" regularized="Î±|digit=1|" original="[Î±|digit=1|]" completeness="fully_reconstructed" tag="numeral.none.none.none" lemma="Î±" lemmaFlag="ok" perseusTag="m--------"/>
      <word wordref_id="2101180" id="87" texid="19879" row="283" wordNum="4" hand="m1" regularized="Î½Î¿Î¼Î¯ÏƒÎ¼Î±Ï„Î±" original="[Î½Î¿(Î¼Î¯ÏƒÎ¼Î±Ï„Î±)]" completeness="fully_reconstructed" tag="noun.pl.neut.acc" lemma="Î½ÏŒÎ¼Î¹ÏƒÎ¼Î±" lemmaFlag="ok" perseusTag="n-p---na-"/>
      <word wordref_id="2101181" id="88" texid="19879" row="283" wordNum="5" hand="m1" regularized="Î¶|digit=7|" original="Î¶|digit=7|" completeness="complete" tag="numeral.none.none.none" lemma="Î¶" lemmaFlag="ok" perseusTag="m--------"/>
      <word wordref_id="2101182" id="89" texid="19879" row="283" wordNum="6" hand="m1" regularized="ð…µ|digit=1/2|" original="ð…µ|digit=1/2|" completeness="complete" tag="numeral.none.none.none" lemma="ð…µ" lemmaFlag="ok" perseusTag="m--------"/>
      <word wordref_id="2101183" id="90" texid="19879" row="283" wordNum="7" hand="m1" regularized="Î²|digit=2|" original="Î²|digit=2|" completeness="complete" tag="numeral.none.none.none" lemma="Î²" lemmaFlag="ok" perseusTag="m--------"/>
      <word wordref_id="2101184" id="91" texid="19879" row="283" wordNum="8" hand="m1" regularized="Î ÎµÎ´Î¹Î¬Î´Ï‰Î½" original="Î ÎµÎ´Î¹(Î¬Î´Ï‰Î½)" completeness="complete" tag="noun.pl.fem.gen" lemma="Î ÎµÎ´Î¹Î¬Ï‚" lemmaFlag="ok" perseusTag="n-p---fg-"/>
      <word wordref_id="2101185" id="92" texid="19879" row="283" wordNum="9" hand="m1" regularized="á¼€Î³Î³Î±ÏÎµÏ…Ï„á½´Ï‚" original="á¼€Î³Î³Ì£(Î±ÏÎµÏ…Ï„á½´Ï‚)" completeness="complete" tag="noun.sg.masc.nom" lemma="á¼€Î³Î³Î±ÏÎµÏ…Ï„Î®Ï‚" lemmaFlag="ok" perseusTag="n-s---mn-"/>
      <word wordref_id="2101186" id="93" texid="19879" row="283" wordNum="10" hand="m1" regularized="Î±|digit=1|" original="Î±|digit=1|" completeness="complete" tag="numeral.none.none.none" lemma="Î±" lemmaFlag="ok" perseusTag="m--------"/>
      <word wordref_id="2101187" id="94" texid="19879" row="283" wordNum="11" hand="m1" regularized="Î½Î¿Î¼Î¯ÏƒÎ¼Î±Ï„Î±" original="Î½Î¿(Î¼Î¯ÏƒÎ¼Î±Ï„Î±)" completeness="complete" tag="noun.pl.neut.acc" lemma="Î½ÏŒÎ¼Î¹ÏƒÎ¼Î±" lemmaFlag="ok" perseusTag="n-p---na-"/>
      <word wordref_id="2101188" id="95" texid="19879" row="283" wordNum="12" hand="m1" regularized="Î³|digit=3|" original="Î³|digit=3|" completeness="complete" tag="numeral.none.none.none" lemma="Î³" lemmaFlag="ok" perseusTag="m--------"/>
      <word wordref_id="2101189" id="96" texid="19879" row="283" wordNum="13" hand="m1" regularized="ð…µ|digit=1/2|" original="ð…µ|digit=1/2|" completeness="complete" tag="numeral.none.none.none" lemma="ð…µ" lemmaFlag="ok" perseusTag="m--------"/>
      <word wordref_id="2101190" id="97" texid="19879" row="283" wordNum="14" hand="m1" regularized="Î´Â´|digit=1/4|" original="Î´Â´|digit=1/4|" completeness="complete" tag="numeral.none.none.none" lemma="Î´Â´" lemmaFlag="ok" perseusTag="m--------"/>
      <word wordref_id="2101191" id="98" texid="19879" row="283" wordNum="15" hand="m1" regularized="Î Î±ÎºÎ±ÏÎ½ÎµÏ‰Ï‚" original="Î Î±ÎºÎ±ÏÎ½(ÎµÏ‰Ï‚)" completeness="complete" tag="noun.sg.fem.gen" lemma="Î Î¬ÎºÎ±Ï…Î½Î¹Ï‚" lemmaFlag="ok" perseusTag="n-s---fg-"/>
      <word wordref_id="2101192" id="99" texid="19879" row="283" wordNum="16" hand="m1" regularized="ÎºÎ±Î»Î±Ï†Î¬Ï„Î·Ï‚" original="ÎºÎ±Î»Î±(Ï†Î¬Ï„Î·Ï‚)" completeness="complete" tag="adjective.sg.fem.gen.pos" lemma="ÎºÎ±Î»Î¬Ï†Î±Ï„Î¿Ï‚" lemmaFlag="suspect" perseusTag="a-s---fg-"/>
      <word wordref_id="2101193" id="100" texid="19879" row="283" wordNum="17" hand="m1" regularized="Î±|digit=1|" original="Î±|digit=1|" completeness="complete" tag="numeral.none.none.none" lemma="Î±" lemmaFlag="ok" perseusTag="m--------"/>
      <word wordref_id="2101194" id="101" texid="19879" row="283" wordNum="18" hand="m1" regularized="Î½Î¿Î¼Î¯ÏƒÎ¼Î±Ï„Î±" original="Î½Î¿(Î¼Î¯ÏƒÎ¼Î±Ï„Î±)" completeness="complete" tag="noun.pl.neut.acc" lemma="Î½ÏŒÎ¼Î¹ÏƒÎ¼Î±" lemmaFlag="ok" perseusTag="n-p---na-"/>
      <word wordref_id="2101195" id="102" texid="19879" row="283" wordNum="19" hand="m1" regularized="Î¶|digit=7|" original="Î¶|digit=7|" completeness="complete" tag="numeral.none.none.none" lemma="Î¶" lemmaFlag="ok" perseusTag="m--------"/>
      <word wordref_id="2101196" id="103" texid="19879" row="283" wordNum="20" hand="m1" regularized="ð…µ|digit=1/2|" original="ð…µ|digit=1/2|" completeness="complete" tag="numeral.none.none.none" lemma="ð…µ" lemmaFlag="ok" perseusTag="m--------"/>
      <word wordref_id="2101197" id="104" texid="19879" row="284" wordNum="1" hand="m1" regularized="|gap=unknown|" original="|gap=unknown|" completeness="incomplete" tag="" lemma="" lemmaFlag="suspect" perseusTag=""/>
      <word wordref_id="2101198" id="105" texid="19879" row="284" wordNum="2" hand="m1" regularized="Î¼ÎµÏ„á½°" original="[Î¼(Îµ)Ï„(á½°)]" completeness="fully_reconstructed" tag="preposition" lemma="Î¼ÎµÏ„Î¬" lemmaFlag="ok" perseusTag="r--------"/>
      <word wordref_id="2101199" id="106" texid="19879" row="284" wordNum="3" hand="m1" regularized="ÎºÎ¿Î¼Î¯ÏƒÎ¼Î±Ï„Î¿Ï‚" original="[ÎºÎ¿Î¼Î¯ÏƒÎ¼(Î±Ï„Î¿Ï‚)]" completeness="fully_reconstructed" tag="noun.sg.neut.gen" lemma="ÎºÏŒÎ¼Î¹ÏƒÎ¼Î±" lemmaFlag="suspect" perseusTag="n-s---ng-"/>
      <word wordref_id="2101200" id="107" texid="19879" row="284" wordNum="4" hand="m1" regularized="ÏƒÎ¯Ï„Î¿Ï…" original="[Ïƒ]Î¯Ï„\Î¿Ï…/" completeness="partly_reconstructed" tag="noun.sg.masc.gen" lemma="Ïƒá¿–Ï„Î¿Ï‚" lemmaFlag="ok" perseusTag="n-s---mg-"/>
      <word wordref_id="2101201" id="108" texid="19879" row="284" wordNum="5" hand="m1" regularized="á¼€Ï€á½¸" original="á¼€Ï€á½¸" completeness="complete" tag="preposition" lemma="á¼€Ï€ÏŒ" lemmaFlag="ok" perseusTag="r--------"/>
      <word wordref_id="2101202" id="109" texid="19879" row="284" wordNum="6" hand="m1" regularized="Ï„Î¿á¿¦" original="Ï„(Î¿á¿¦)" completeness="complete" tag="article.sg.masc.gen" lemma="á½" lemmaFlag="ok" perseusTag="l-s---mg-"/>
      <word wordref_id="2101203" id="110" texid="19879" row="284" wordNum="7" hand="m1" regularized="Î¤Î¿Ï…Ï‰" original="Î¤Î¿Ï…Ï‰" completeness="complete" tag="noun.sg.masc.gen" lemma="Î¤Î¿ÏÏ‰" lemmaFlag="ok" perseusTag="n-s---mg-"/>
      <word wordref_id="2101204" id="111" texid="19879" row="284" wordNum="8" hand="m1" regularized="á¼•Ï‰Ï‚" original="á¼•Ï‰Ï‚" completeness="complete" tag="preposition" lemma="á¼•Ï‰Ï‚" lemmaFlag="ok" perseusTag="r--------"/>
      <word wordref_id="2101205" id="112" texid="19879" row="284" wordNum="9" hand="m1" regularized="Ï„Î¿á¿¦" original="Ï„\Î¿á¿¦/" completeness="complete" tag="article.sg.neut.gen" lemma="á½" lemmaFlag="ok" perseusTag="l-s---ng-"/>
      <word wordref_id="2101206" id="113" texid="19879" row="284" wordNum="10" hand="m1" regularized="ÎšÎ»ÏÏƒÎ¼Î±Ï„Î¿Ï‚" original="ÎšÎ»Ï(ÏƒÎ¼Î±Ï„Î¿Ï‚)" completeness="complete" tag="noun.sg.neut.gen" lemma="ÎšÎ»ÏÏƒÎ¼Î±" lemmaFlag="ok" perseusTag="n-s---ng-"/>
      <word wordref_id="2101207" id="114" texid="19879" row="284" wordNum="11" hand="m1" regularized="Î¼Î·Î½á¿¶Î½" original="Î¼(Î·Î½á¿¶Î½)" completeness="complete" tag="noun.pl.masc.gen" lemma="Î¼Î®Î½" lemmaFlag="ok" perseusTag="n-p---mg-"/>
      <word wordref_id="2101208" id="115" texid="19879" row="284" wordNum="12" hand="m1" regularized="Î´|digit=4|" original="Î´|digit=4|" completeness="complete" tag="numeral.none.none.none" lemma="Î´" lemmaFlag="ok" perseusTag="m--------"/>
      <word wordref_id="2101209" id="116" texid="19879" row="284" wordNum="13" hand="m1" regularized="Î¿á½•Ï„Ï‰Ï‚" original="Î¿Ì£á½•Ì£Ï„Ì£[Ï‰(Ï‚)]" completeness="partly_reconstructed" tag="adverb" lemma="Î¿á½•Ï„Ï‰Ï‚" lemmaFlag="ok" perseusTag="d--------"/>
      <word wordref_id="2101210" id="117" texid="19879" row="284" wordNum="14" hand="m1" regularized="ÎºÎ±Î»Î±Ï†Î¬Ï„Î±Î¹" original="[ÎºÎ±]Î»Ì£(Î±Ï†Î¬Ï„Î±Î¹)" completeness="partly_reconstructed" tag="noun.pl.masc.nom" lemma="ÎºÎ±Î»Î·Ï†Î¬Ï„Î·Ï‚" lemmaFlag="suspect" perseusTag="n-p---mn-"/>
      <word wordref_id="2101211" id="118" texid="19879" row="284" wordNum="15" hand="m1" regularized="Î²|digit=2|" original="Î²|digit=2|" completeness="complete" tag="numeral.none.none.none" lemma="Î²" lemmaFlag="ok" perseusTag="m--------"/>
      <word wordref_id="2101212" id="119" texid="19879" row="284" wordNum="16" hand="m1" regularized="Î½Î¿Î¼Î¯ÏƒÎ¼Î±Ï„Î±" original="Î½Î¿(Î¼Î¯ÏƒÎ¼Î±Ï„Î±)" completeness="complete" tag="noun.pl.neut.nom" lemma="Î½ÏŒÎ¼Î¹ÏƒÎ¼Î±" lemmaFlag="ok" perseusTag="n-p---nn-"/>
      <word wordref_id="2101213" id="120" texid="19879" row="284" wordNum="17" hand="m1" regularized="Î¹Î²|digit=12|" original="Î¹Î²|digit=12|" completeness="complete" tag="numeral.none.none.none" lemma="Î¹Î²" lemmaFlag="ok" perseusTag="m--------"/>
      <word wordref_id="2101214" id="121" texid="19879" row="284" wordNum="18" hand="m1" regularized="Ï„Î­ÎºÏ„Ï‰Î½" original="Ï„Î­(ÎºÏ„Ï‰Î½)" completeness="complete" tag="noun.sg.masc.nom" lemma="Ï„Î­ÎºÏ„Ï‰Î½" lemmaFlag="ok" perseusTag="n-s---mn-"/>
      <word wordref_id="2101215" id="122" texid="19879" row="284" wordNum="19" hand="m1" regularized="Î±|digit=1|" original="Î±|digit=1|" completeness="complete" tag="numeral.none.none.none" lemma="Î±" lemmaFlag="ok" perseusTag="m--------"/>
      <word wordref_id="2101216" id="123" texid="19879" row="284" wordNum="20" hand="m1" regularized="Î½Î¿Î¼Î¯ÏƒÎ¼Î±Ï„Î±" original="Î½Î¿(Î¼Î¯ÏƒÎ¼Î±Ï„Î±)" completeness="complete" tag="noun.pl.neut.acc" lemma="Î½ÏŒÎ¼Î¹ÏƒÎ¼Î±" lemmaFlag="ok" perseusTag="n-p---na-"/>
      <word wordref_id="2101217" id="124" texid="19879" row="284" wordNum="21" hand="m1" regularized="Îµ|digit=5|" original="Îµ|digit=5|" completeness="complete" tag="numeral.none.none.none" lemma="Îµ" lemmaFlag="ok" perseusTag="m--------"/>
      <word wordref_id="2101218" id="125" texid="19879" row="285" wordNum="1" hand="m1" regularized="|gap=unknown|" original="|gap=unknown|" completeness="incomplete" tag="" lemma="" lemmaFlag="suspect" perseusTag=""/>
      <word wordref_id="2101219" id="126" texid="19879" row="285" wordNum="2" hand="m1" regularized="ÎºÎ±Î»Î±Ï†Î¬Ï„Î¿Ï…" original="ÎºÎ±Î»Î±(Ï†Î¬Ï„Î¿Ï…)" completeness="complete" tag="noun.sg.neut.gen" lemma="ÎºÎ±Î»Î¬Ï†Î±Ï„Î¿Î½" lemmaFlag="suspect" perseusTag="n-s---ng-"/>
      <word wordref_id="2101220" id="127" texid="19879" row="285" wordNum="3" hand="m1" regularized="ð…µ|digit=1/2|" original="ð…µ|digit=1/2|" completeness="complete" tag="numeral.none.none.none" lemma="ð…µ" lemmaFlag="ok" perseusTag="m--------"/>
      <word wordref_id="2101221" id="128" texid="19879" row="285" wordNum="4" hand="m1" regularized="Î½Î¿Î¼Î¯ÏƒÎ¼Î±Ï„Î±" original="Î½Î¿(Î¼Î¯ÏƒÎ¼Î±Ï„Î±)" completeness="complete" tag="noun.pl.neut.acc" lemma="Î½ÏŒÎ¼Î¹ÏƒÎ¼Î±" lemmaFlag="ok" perseusTag="n-p---na-"/>
      <word wordref_id="2101222" id="129" texid="19879" row="285" wordNum="5" hand="m1" regularized="Î³|digit=3|" original="Î³|digit=3|" completeness="complete" tag="numeral.none.none.none" lemma="Î³" lemmaFlag="ok" perseusTag="m--------"/>
      <word wordref_id="2101223" id="130" texid="19879" row="285" wordNum="6" hand="m1" regularized="Î Î±ÎºÎ±ÏÎ½ÎµÏ‰Ï‚" original="Î Î±ÎºÎ±ÏÎ½(ÎµÏ‰Ï‚)" completeness="complete" tag="noun.sg.none.gen" lemma="Î Î¬ÎºÎ±Ï…Î½Î¹Ï‚" lemmaFlag="ok" perseusTag="n-s----g-"/>
      <word wordref_id="2101224" id="131" texid="19879" row="285" wordNum="7" hand="m1" regularized="ÎºÎ±Î»Î±Ï†Î¬Ï„Î¿Ï…" original="ÎºÎ±Î»(Î±Ï†Î¬Ï„Î¿Ï…)" completeness="complete" tag="noun.sg.masc.gen" lemma="ÎºÎ±Î»Î¬Ï†Î±Ï„Î¿Ï‚" lemmaFlag="suspect" perseusTag="n-s---mg-"/>
      <word wordref_id="2101225" id="132" texid="19879" row="285" wordNum="8" hand="m1" regularized="ð…µ|digit=1/2|" original="ð…µ|digit=1/2|" completeness="complete" tag="numeral.none.none.none" lemma="ð…µ" lemmaFlag="ok" perseusTag="m--------"/>
      <word wordref_id="2101226" id="133" texid="19879" row="285" wordNum="9" hand="m1" regularized="Î½Î¿Î¼Î¯ÏƒÎ¼Î±Ï„Î±" original="Î½Î¿(Î¼Î¯ÏƒÎ¼Î±Ï„Î±)" completeness="complete" tag="noun.pl.neut.acc" lemma="Î½ÏŒÎ¼Î¹ÏƒÎ¼Î±" lemmaFlag="ok" perseusTag="n-p---na-"/>
      <word wordref_id="2101227" id="134" texid="19879" row="285" wordNum="10" hand="m1" regularized="Î³|digit=3|" original="Î³|digit=3|" completeness="complete" tag="numeral.none.none.none" lemma="Î³" lemmaFlag="ok" perseusTag="m--------"/>
      <word wordref_id="2101228" id="135" texid="19879" row="286" wordNum="1" hand="m1" regularized="|gap=unknown|" original="|gap=unknown|" completeness="incomplete" tag="" lemma="" lemmaFlag="suspect" perseusTag=""/>
      <word wordref_id="2101229" id="136" texid="19879" row="286" wordNum="2" hand="m1" regularized="Î¼Î·Î½á¿¶Î½" original="Î¼(Î·Î½á¿¶Î½)" completeness="complete" tag="noun.pl.masc.gen" lemma="Î¼Î®Î½" lemmaFlag="ok" perseusTag="n-p---mg-"/>
      <word wordref_id="2101230" id="137" texid="19879" row="286" wordNum="3" hand="m1" regularized="Ï›|digit=6|" original="Ï›|digit=6|" completeness="complete" tag="numeral.none.none.none" lemma="Ï›" lemmaFlag="ok" perseusTag="m--------"/>
      <word wordref_id="2101231" id="138" texid="19879" row="286" wordNum="4" hand="m1" regularized="Î´Î¹á½°" original="Î´(Î¹á½°)" completeness="complete" tag="preposition" lemma="Î´Î¹Î¬" lemmaFlag="ok" perseusTag="r--------"/>
      <word wordref_id="2101232" id="139" texid="19879" row="286" wordNum="5" hand="m1" regularized="Ï„á¿†Ï‚" original="Ï„(á¿†Ï‚)" completeness="complete" tag="article.sg.fem.gen" lemma="á½" lemmaFlag="ok" perseusTag="l-s---fg-"/>
      <word wordref_id="2101233" id="140" texid="19879" row="286" wordNum="6" hand="m1" regularized="ÎºÏŽÎ¼Î·Ï‚" original="ÎºÏŽÎ¼Î·(Ï‚)" completeness="complete" tag="noun.sg.fem.gen" lemma="ÎºÏŽÎ¼Î·" lemmaFlag="ok" perseusTag="n-s---fg-"/>
      <word wordref_id="2101234" id="141" texid="19879" row="286" wordNum="7" hand="m1" regularized="á¼ˆÏ†ÏÎ¿Î´Î¹Ï„á½¼" original="á¼ˆÏ†ÏÎ¿Î´(Î¹Ï„á½¼)" completeness="complete" tag="noun.sg.fem.nom" lemma="á¼ˆÏ†ÏÎ¿Î´Î¹Ï„ÏŽ" lemmaFlag="ok" perseusTag="n-s---fn-"/>
      <word wordref_id="2101235" id="142" texid="19879" row="286" wordNum="8" hand="m1" regularized="ÎºÎ±Î»Î±Ï†Î¬Ï„Î·Ï‚" original="ÎºÎ±Î»Î±(Ï†Î¬Ï„Î·Ï‚)" completeness="complete" tag="noun.sg.fem.gen" lemma="ÎºÎ±Î»Î±Ï†Î¬Ï„Î·" lemmaFlag="suspect" perseusTag="n-s---fg-"/>
      <word wordref_id="2101236" id="143" texid="19879" row="286" wordNum="9" hand="m1" regularized="Î±|digit=1|" original="Î±|digit=1|" completeness="complete" tag="numeral.none.none.none" lemma="Î±" lemmaFlag="ok" perseusTag="m--------"/>
      <word wordref_id="2101237" id="144" texid="19879" row="286" wordNum="10" hand="m1" regularized="Î½Î¿Î¼Î¯ÏƒÎ¼Î±Ï„Î±" original="Î½Î¿(Î¼Î¯ÏƒÎ¼Î±Ï„Î±)" completeness="complete" tag="noun.pl.neut.acc" lemma="Î½ÏŒÎ¼Î¹ÏƒÎ¼Î±" lemmaFlag="ok" perseusTag="n-p---na-"/>
      <word wordref_id="2101238" id="145" texid="19879" row="286" wordNum="11" hand="m1" regularized="Î¸|digit=9|" original="Î¸|digit=9|" completeness="complete" tag="numeral.none.none.none" lemma="Î¸" lemmaFlag="ok" perseusTag="m--------"/>
      <word wordref_id="2101239" id="146" texid="19879" row="286" wordNum="12" hand="m1" regularized="ð…µ|digit=1/2|" original="ð…µ|digit=1/2|" completeness="complete" tag="numeral.none.none.none" lemma="ð…µ" lemmaFlag="ok" perseusTag="m--------"/>
      <word wordref_id="2101240" id="147" texid="19879" row="287" wordNum="1" hand="m1" regularized="|gap=unknown|" original="|gap=unknown|" completeness="incomplete" tag="" lemma="" lemmaFlag="suspect" perseusTag=""/>
      <word wordref_id="2101241" id="148" texid="19879" row="287" wordNum="2" hand="m1" regularized="Î½Î¿Î¼Î¯ÏƒÎ¼Î±Ï„Î±" original="Î½Î¿(Î¼Î¯ÏƒÎ¼Î±Ï„Î±)" completeness="complete" tag="noun.pl.neut.acc" lemma="Î½ÏŒÎ¼Î¹ÏƒÎ¼Î±" lemmaFlag="ok" perseusTag="n-p---na-"/>
      <word wordref_id="2101242" id="149" texid="19879" row="287" wordNum="3" hand="m1" regularized="Îº|digit=20|" original="Îº|digit=20|" completeness="complete" tag="numeral.none.none.none" lemma="Îº" lemmaFlag="ok" perseusTag="m--------"/>
      <word wordref_id="2101243" id="150" texid="19879" row="287" wordNum="4" hand="m1" regularized="ð…·|digit=2/3|" original="ð…·|digit=2/3|" completeness="complete" tag="numeral.none.none.none" lemma="ð…·" lemmaFlag="ok" perseusTag="m--------"/>
      <word wordref_id="2101244" id="151" texid="19879" row="287" wordNum="5" hand="m1" regularized="Î·Â´|digit=1/8|" original="Î·Â´|digit=1/8|" completeness="complete" tag="numeral.none.none.none" lemma="Î·Â´" lemmaFlag="ok" perseusTag="m--------"/>
      <word wordref_id="2101245" id="152" texid="19879" row="288" wordNum="1" hand="m1" regularized="|gap=unknown|" original="|gap=unknown|" completeness="incomplete" tag="" lemma="" lemmaFlag="suspect" perseusTag=""/>
      <word wordref_id="2101246" id="153" texid="19879" row="288" wordNum="2" hand="m1" regularized="Ïƒá½ºÎ½" original="Ïƒá½º(Î½)" completeness="complete" tag="preposition" lemma="ÏƒÏÎ½" lemmaFlag="ok" perseusTag="r--------"/>
      <word wordref_id="2101247" id="154" texid="19879" row="288" wordNum="3" hand="m1" regularized="Î½Î¿Î¼Î¯ÏƒÎ¼Î±ÏƒÎ¹" original="Î½Î¿(Î¼Î¯ÏƒÎ¼Î±ÏƒÎ¹)" completeness="complete" tag="noun.pl.neut.dat" lemma="Î½ÏŒÎ¼Î¹ÏƒÎ¼Î±" lemmaFlag="ok" perseusTag="n-p---nd-"/>
      <word wordref_id="2101248" id="155" texid="19879" row="288" wordNum="4" hand="m1" regularized="Î³|digit=3|" original="Î³|digit=3|" completeness="complete" tag="numeral.none.none.none" lemma="Î³" lemmaFlag="ok" perseusTag="m--------"/>
      <word wordref_id="2101249" id="156" texid="19879" row="288" wordNum="5" hand="m1" regularized="Î´Î¹á½°" original="Î´(Î¹á½°)" completeness="complete" tag="preposition" lemma="Î´Î¹Î¬" lemmaFlag="ok" perseusTag="r--------"/>
      <word wordref_id="2101250" id="157" texid="19879" row="288" wordNum="6" hand="m1" regularized="Ï„á¿¶Î½" original="Ï„(á¿¶Î½)" completeness="complete" tag="article.pl.neut.gen" lemma="á½" lemmaFlag="ok" perseusTag="l-p---ng-"/>
      <word wordref_id="2101251" id="158" texid="19879" row="288" wordNum="7" hand="m1" regularized="á½„Î½Ï„Ï‰Î½" original="á½„Î½(Ï„Ï‰Î½)" completeness="complete" tag="participle.pl.pres.act.neut.gen" lemma="Îµá¼°Î¼Î¯" lemmaFlag="ok" perseusTag="v-pppang-"/>
      <word wordref_id="2101252" id="159" texid="19879" row="288" wordNum="8" hand="m1" regularized="á¼Î½" original="á¼Î½" completeness="complete" tag="preposition" lemma="á¼Î½" lemmaFlag="ok" perseusTag="r--------"/>
      <word wordref_id="2101253" id="160" texid="19879" row="288" wordNum="9" hand="m1" regularized="Î’Î±Î²Ï…Î»á¿¶Î½Î¹" original="Î’Î±Î²(Ï…)Î»(á¿¶Î½Î¹)" completeness="complete" tag="noun.sg.fem.dat" lemma="Î’Î±Î²Ï…Î»ÏŽÎ½" lemmaFlag="ok" perseusTag="n-s---fd-"/>
      <word wordref_id="2101254" id="161" texid="19879" row="288" wordNum="10" hand="m1" regularized="Î½Î¿Î¼Î¯ÏƒÎ¼Î±Ï„Î±" original="Î½Î¿(Î¼Î¯ÏƒÎ¼Î±Ï„Î±)" completeness="complete" tag="noun.pl.neut.acc" lemma="Î½ÏŒÎ¼Î¹ÏƒÎ¼Î±" lemmaFlag="ok" perseusTag="n-p---na-"/>
      <word wordref_id="2101255" id="162" texid="19879" row="288" wordNum="11" hand="m1" regularized="ÎºÎ·|digit=28|" original="ÎºÎ·|digit=28|" completeness="complete" tag="numeral.none.none.none" lemma="ÎºÎ·" lemmaFlag="ok" perseusTag="m--------"/>
      <word wordref_id="2101256" id="163" texid="19879" row="289" wordNum="1" hand="m1" regularized="|gap=unknown|" original="|gap=unknown|" completeness="incomplete" tag="" lemma="" lemmaFlag="suspect" perseusTag=""/>
      <word wordref_id="2101257" id="164" texid="19879" row="289" wordNum="2" hand="m1" regularized="Î½Î¿Î¼Î¯ÏƒÎ¼Î±Ï„Î±" original="Î½Î¿(Î¼Î¯ÏƒÎ¼Î±Ï„Î±)" completeness="complete" tag="noun.pl.neut.acc" lemma="Î½ÏŒÎ¼Î¹ÏƒÎ¼Î±" lemmaFlag="ok" perseusTag="n-p---na-"/>
      <word wordref_id="2101258" id="165" texid="19879" row="289" wordNum="3" hand="m1" regularized="Î²|digit=2|" original="Î²|digit=2|" completeness="complete" tag="numeral.none.none.none" lemma="Î²" lemmaFlag="ok" perseusTag="m--------"/>
      <word wordref_id="2101259" id="166" texid="19879" row="289" wordNum="4" hand="m1" regularized="ð…µ|digit=1/2|" original="ð…µ|digit=1/2|" completeness="complete" tag="numeral.none.none.none" lemma="ð…µ" lemmaFlag="ok" perseusTag="m--------"/>
      <word wordref_id="2101260" id="167" texid="19879" row="290" wordNum="1" hand="m1" regularized="|gap=unknown|" original="|gap=unknown|" completeness="incomplete" tag="" lemma="" lemmaFlag="suspect" perseusTag=""/>
      <word wordref_id="2101261" id="168" texid="19879" row="290" wordNum="2" hand="m1" regularized="Î½Î¿Î¼Î¯ÏƒÎ¼Î±Ï„Î±" original="Î½Î¿(Î¼Î¯ÏƒÎ¼Î±Ï„Î±)" completeness="complete" tag="noun.pl.neut.acc" lemma="Î½ÏŒÎ¼Î¹ÏƒÎ¼Î±" lemmaFlag="ok" perseusTag="n-p---na-"/>
      <word wordref_id="2101262" id="169" texid="19879" row="290" wordNum="3" hand="m1" regularized="Î¶|digit=7|" original="Î¶|digit=7|" completeness="complete" tag="numeral.none.none.none" lemma="Î¶" lemmaFlag="ok" perseusTag="m--------"/>
      <word wordref_id="2101263" id="170" texid="19879" row="290" wordNum="4" hand="m1" regularized="Î³Â´|digit=1/3|" original="Î³Â´|digit=1/3|" completeness="complete" tag="numeral.none.none.none" lemma="Î³Â´" lemmaFlag="ok" perseusTag="m--------"/>
      <word wordref_id="2101264" id="171" texid="19879" row="290" wordNum="5" hand="m1" regularized="ÎºÎ´Â´|digit=1/24|" original="ÎºÎ´Â´|digit=1/24|" completeness="complete" tag="numeral.none.none.none" lemma="ÎºÎ´Â´" lemmaFlag="ok" perseusTag="m--------"/>
    </sentence>
  </text>
</file>
