<?xml version="1.0" encoding="UTF-8"?>
<file name="upz.1.150" TM="3542" HGV="3542" lang="grc" textpart="2">
	<text>
		<sentence id="1">
			<word wordref_id="4672832" id="1" texid="3542" row="24" wordNum="1" hand="m1" regularized="|gap=1_lines|" original="|gap=1_lines|" completeness="incomplete" tag="" lemma="" lemmaFlag="suspect"/>
			<word wordref_id="4672833" id="2" texid="3542" row="25" wordNum="1" hand="m1" regularized="χαλκοῦ" original="χα(λκοῦ)" completeness="complete" tag="noun.sg.masc.gen" lemma="χαλκός" lemmaFlag="ok"/>
			<word wordref_id="4672834" id="3" texid="3542" row="25" wordNum="2" hand="m1" regularized="τάλαντ…" original="(τάλαντ…)" completeness="complete" tag="" lemma="" lemmaFlag="suspect"/>
			<word wordref_id="4672835" id="4" texid="3542" row="25" wordNum="3" hand="m1" regularized="|gap=unknown|" original="|gap=unknown|" completeness="incomplete" tag="" lemma="" lemmaFlag="suspect"/>
			<word wordref_id="4672836" id="5" texid="3542" row="26" wordNum="1" hand="m1" regularized="κε|gap=2|" original="κε̣|gap=2|" completeness="incomplete" tag="" lemma="" lemmaFlag="suspect"/>
			<word wordref_id="4672837" id="6" texid="3542" row="27" wordNum="1" hand="m1" regularized="τὸ" original="τὸ" completeness="complete" tag="article.sg.neut.nom" lemma="ὁ" lemmaFlag="ok"/>
			<word wordref_id="4672838" id="7" texid="3542" row="27" wordNum="2" hand="m1" regularized="δὲ" original="δὲ" completeness="complete" tag="particle" lemma="δέ" lemmaFlag="ok"/>
			<word wordref_id="4672839" id="8" texid="3542" row="27" wordNum="3" hand="m1" regularized="η|gap=unknown|" original="η̣|gap=unknown|" completeness="incomplete" tag="" lemma="" lemmaFlag="suspect"/>
			<word wordref_id="4672840" id="9" texid="3542" row="28" wordNum="1" hand="m1" regularized="κεφαλαι" original="κεφαλ[αι]" completeness="partly_reconstructed" tag="noun.pl.fem.nom" lemma="κεφαλή" lemmaFlag="ok"/>
			<word wordref_id="4672841" id="10" texid="3542" row="28" wordNum="2" hand="m1" regularized="|gap=unknown|" original="|gap=unknown|" completeness="incomplete" tag="" lemma="" lemmaFlag="suspect"/>
			<word wordref_id="4672842" id="11" texid="3542" row="29" wordNum="1" hand="m1" regularized="|gap=1_lines|" original="|gap=1_lines|" completeness="incomplete" tag="" lemma="" lemmaFlag="suspect"/>
		</sentence>
	</text>
</file>
